w_dao/__cls_aide_dao_action__.py
w_dao/__cls_aide_dao_model__.py
w_dao/__example_cls_dao_model__.py
w_dao/__init__.py
w_dao-1.2.dist-info/METADATA
w_dao-1.2.dist-info/WHEEL
w_dao-1.2.dist-info/top_level.txt
w_dao-1.2.dist-info/RECORD
