Metadata-Version: 2.1
Name: w-dao
Version: 1.2
Summary: A useless database access model
Home-page: https://github.com/zzt/w-dao.git
Author: zzt
Author-email: zzt@qq.com
License: MIT
Keywords: w_dao
